README.rst
setup.py
flake8_junit_report.egg-info/PKG-INFO
flake8_junit_report.egg-info/SOURCES.txt
flake8_junit_report.egg-info/dependency_links.txt
flake8_junit_report.egg-info/entry_points.txt
flake8_junit_report.egg-info/top_level.txt
junit_conversor/__about__.py
junit_conversor/__init__.py
junit_conversor/__main__.py