Metadata-Version: 1.1
Name: flake8-junit-report
Version: 2.1.0
Summary: Simple tool that converts a flake8 file to junit format
Home-page: https://github.com/initios/flake8-junit-report
Author: Carlos Goce
Author-email: carlosgoce@gmail.com
License: BSD 3-Clause License
Platform: UNKNOWN
Classifier: Programming Language :: Python
Classifier: Programming Language :: Python :: 2.6
Classifier: Programming Language :: Python :: 2.7
Classifier: Programming Language :: Python :: 3.4
Classifier: Development Status :: 5 - Production/Stable
Classifier: License :: OSI Approved :: BSD License
